cogvi/__init__.py
cogvi/cogvi.py
cogvi-0.1.dist-info/DESCRIPTION.rst
cogvi-0.1.dist-info/METADATA
cogvi-0.1.dist-info/RECORD
cogvi-0.1.dist-info/WHEEL
cogvi-0.1.dist-info/metadata.json
cogvi-0.1.dist-info/top_level.txt
