Metadata-Version: 2.0
Name: cogvi
Version: 0.1
Summary: AI Lib
Home-page: https://github.com/gautam0707/cogvi
Author: Gautam A
Author-email: bgautam0707@gmail.com
License: UNKNOWN
Download-URL: https://github.com/gautam0707/cogvi/archive/0.1.tar.gz
Keywords: ai,agi,ml
Platform: UNKNOWN
